multimethod.py
multimethod_dispatcher-1.0.2.dist-info/LICENSE
multimethod_dispatcher-1.0.2.dist-info/METADATA
multimethod_dispatcher-1.0.2.dist-info/WHEEL
multimethod_dispatcher-1.0.2.dist-info/top_level.txt
multimethod_dispatcher-1.0.2.dist-info/RECORD
