Metadata-Version: 2.1
Name: multimethod-dispatcher
Version: 1.0.2
Summary: A clojure style multimethod dispatcher
Home-page: https://github.com/sanjP10/multimethod.git
Author: Sanjay Patel
Author-email: sanjay10.patel@gmail.com
License: UNKNOWN
Keywords: multimethod dispatcher functional-programming
Platform: UNKNOWN
Classifier: Programming Language :: Python :: 3
Classifier: Programming Language :: Python :: 3.6
Classifier: Programming Language :: Python :: 3.7
Classifier: Programming Language :: Python :: 3.8
Classifier: Programming Language :: Python :: 3.9
Classifier: License :: OSI Approved :: Apache Software License
Classifier: Operating System :: OS Independent
Classifier: Development Status :: 5 - Production/Stable
Classifier: Intended Audience :: Developers
License-File: LICENSE
Provides-Extra: dev
Requires-Dist: pylint (>=2.6) ; extra == 'dev'
Requires-Dist: coverage (>=5.4) ; extra == 'dev'
Provides-Extra: publishing
Requires-Dist: twine (>=3.3) ; extra == 'publishing'
